hcl2/__init__.py
hcl2/__main__.py
hcl2/api.py
hcl2/hcl2.lark
hcl2/parser.py
hcl2/py.typed
hcl2/transformer.py
test/__init__.py
test/helpers/__init__.py
test/unit/__init__.py
test/unit/test_load.py
test/unit/test_load_with_meta.py
glitch_python_hcl2-0.1.4.dist-info/LICENSE
glitch_python_hcl2-0.1.4.dist-info/METADATA
glitch_python_hcl2-0.1.4.dist-info/WHEEL
glitch_python_hcl2-0.1.4.dist-info/top_level.txt
glitch_python_hcl2-0.1.4.dist-info/RECORD
