Metadata-Version: 2.1
Name: glitch-python-hcl2
Version: 0.1.4
Summary: A parser for HCL2
Home-page: https://github.com/joaotgoncalves/python-hcl2
Author: João Gonçalves
Author-email: joao.marques.goncalves@tecnico.ulisboa.pt
License: MIT
Classifier: Topic :: Software Development :: Libraries :: Python Modules
Classifier: Intended Audience :: Developers
Classifier: License :: OSI Approved :: MIT License
Classifier: Operating System :: OS Independent
Classifier: Programming Language :: Python
Classifier: Programming Language :: Python :: 3
Classifier: Programming Language :: Python :: 3.7
Classifier: Programming Language :: Python :: 3.8
Classifier: Programming Language :: Python :: 3.9
Classifier: Programming Language :: Python :: 3.10
Classifier: Programming Language :: Python :: 3.11
Requires-Python: >=3.7
License-File: LICENSE
Requires-Dist: lark (<2.0,>=1.1.5)
